ccopenai/__init__.py
ccopenai/__main__.py
ccopenai/_base_client.py
ccopenai/_client.py
ccopenai/_compat.py
ccopenai/_constants.py
ccopenai/_exceptions.py
ccopenai/_files.py
ccopenai/_legacy_response.py
ccopenai/_models.py
ccopenai/_module_client.py
ccopenai/_qs.py
ccopenai/_resource.py
ccopenai/_response.py
ccopenai/_streaming.py
ccopenai/_types.py
ccopenai/_version.py
ccopenai/custom_response.py
ccopenai/env.py
ccopenai/pagination.py
ccopenai/prepare.py
ccopenai/py.typed
ccopenai/version.py
ccopenai/_extras/__init__.py
ccopenai/_extras/_common.py
ccopenai/_extras/numpy_proxy.py
ccopenai/_extras/pandas_proxy.py
ccopenai/_extras/sounddevice_proxy.py
ccopenai/_utils/__init__.py
ccopenai/_utils/_logs.py
ccopenai/_utils/_proxy.py
ccopenai/_utils/_reflection.py
ccopenai/_utils/_resources_proxy.py
ccopenai/_utils/_streams.py
ccopenai/_utils/_sync.py
ccopenai/_utils/_transform.py
ccopenai/_utils/_typing.py
ccopenai/_utils/_utils.py
ccopenai/cli/__init__.py
ccopenai/cli/_cli.py
ccopenai/cli/_errors.py
ccopenai/cli/_models.py
ccopenai/cli/_progress.py
ccopenai/cli/_utils.py
ccopenai/cli/_api/__init__.py
ccopenai/cli/_api/_main.py
ccopenai/cli/_api/audio.py
ccopenai/cli/_api/completions.py
ccopenai/cli/_api/files.py
ccopenai/cli/_api/image.py
ccopenai/cli/_api/models.py
ccopenai/cli/_api/chat/__init__.py
ccopenai/cli/_api/chat/completions.py
ccopenai/cli/_tools/__init__.py
ccopenai/cli/_tools/_main.py
ccopenai/cli/_tools/fine_tunes.py
ccopenai/cli/_tools/migrate.py
ccopenai/crypto/__init__.py
ccopenai/crypto/asymm.py
ccopenai/crypto/constants.py
ccopenai/crypto/jwt.py
ccopenai/crypto/symm.py
ccopenai/crypto/util.py
ccopenai/helpers/__init__.py
ccopenai/helpers/local_audio_player.py
ccopenai/helpers/microphone.py
ccopenai/lib/.keep
ccopenai/lib/__init__.py
ccopenai/lib/_old_api.py
ccopenai/lib/_pydantic.py
ccopenai/lib/_tools.py
ccopenai/lib/_validators.py
ccopenai/lib/azure.py
ccopenai/lib/_parsing/__init__.py
ccopenai/lib/_parsing/_completions.py
ccopenai-1.91.1.dist-info/METADATA
ccopenai-1.91.1.dist-info/WHEEL
ccopenai-1.91.1.dist-info/entry_points.txt
ccopenai-1.91.1.dist-info/licenses/LICENSE
ccopenai-1.91.1.dist-info/RECORD
