Metadata-Version: 2.3
Name: ccopenai
Version: 1.91.1
Summary: The official Python library for the openai API
Project-URL: Homepage, https://github.com/openai/openai-python
Project-URL: Repository, https://github.com/openai/openai-python
Author-email: OpenAI <support@openai.com>
License: Apache-2.0
Classifier: Intended Audience :: Developers
Classifier: License :: OSI Approved :: Apache Software License
Classifier: Operating System :: MacOS
Classifier: Operating System :: Microsoft :: Windows
Classifier: Operating System :: OS Independent
Classifier: Operating System :: POSIX
Classifier: Operating System :: POSIX :: Linux
Classifier: Programming Language :: Python :: 3.8
Classifier: Programming Language :: Python :: 3.9
Classifier: Programming Language :: Python :: 3.10
Classifier: Programming Language :: Python :: 3.11
Classifier: Programming Language :: Python :: 3.12
Classifier: Topic :: Software Development :: Libraries :: Python Modules
Classifier: Typing :: Typed
Requires-Python: >=3.8
Requires-Dist: anyio<5,>=3.5.0
Requires-Dist: cryptography>=43.0.3
Requires-Dist: distro<2,>=1.7.0
Requires-Dist: httpx<1,>=0.23.0
Requires-Dist: jiter<1,>=0.4.0
Requires-Dist: pydantic<3,>=1.9.0
Requires-Dist: sniffio
Requires-Dist: tqdm>4
Requires-Dist: trustflow-verification<0.5.0,>=0.4.0.dev20251023
Requires-Dist: typing-extensions<5,>=4.11
Provides-Extra: aiohttp
Requires-Dist: aiohttp; extra == 'aiohttp'
Requires-Dist: httpx-aiohttp>=0.1.6; extra == 'aiohttp'
Provides-Extra: datalib
Requires-Dist: numpy>=1; extra == 'datalib'
Requires-Dist: pandas-stubs>=1.1.0.11; extra == 'datalib'
Requires-Dist: pandas>=1.2.3; extra == 'datalib'
Provides-Extra: realtime
Requires-Dist: websockets<16,>=13; extra == 'realtime'
Provides-Extra: voice-helpers
Requires-Dist: numpy>=2.0.2; extra == 'voice-helpers'
Requires-Dist: sounddevice>=0.5.1; extra == 'voice-helpers'
